antu_package/excute_time.py
timemeter-0.0.1.dist-info/METADATA
timemeter-0.0.1.dist-info/WHEEL
timemeter-0.0.1.dist-info/licenses/LICENSE
timemeter-0.0.1.dist-info/RECORD
