Metadata-Version: 2.1
Name: timemeter
Version: 0.0.1
Summary: This package is a test of How to upload a python package to PiPy?
Project-URL: Homepage, https://github.com/AntuBoccalandro/my_own_python_package
Project-URL: Bug Tracker, https://github.com/albertorc87/subir-paquete-pypi/issues
Author-email: Antu_Bocc <antuboccalandro5@gmail.com>
License: MIT License
License-File: LICENSE
Classifier: License :: OSI Approved :: MIT License
Classifier: Operating System :: OS Independent
Classifier: Programming Language :: Python :: 3
Requires-Python: >=3.9
